tom_astrosource/__init__.py
tom_astrosource/models.py
tom_astrosource/tests.py
tom_astrosource/migrations/0001_initial.py
tom_astrosource/migrations/0002_auto_20190730_1232.py
tom_astrosource/migrations/__init__.py
tom_astrosource-0.1.4.dist-info/LICENSE
tom_astrosource-0.1.4.dist-info/METADATA
tom_astrosource-0.1.4.dist-info/WHEEL
tom_astrosource-0.1.4.dist-info/top_level.txt
tom_astrosource-0.1.4.dist-info/RECORD
