Metadata-Version: 2.1
Name: tom-astrosource
Version: 0.1.4
Summary: Astrosource pipeline for tom_education
Home-page: UNKNOWN
Author: Joe Singleton
Author-email: joesingo@gmail.com
Maintainer: Edward Gomez
Maintainer-email: egomez@lco.global
License: UNKNOWN
Platform: UNKNOWN
Classifier: Programming Language :: Python :: 3
Classifier: License :: OSI Approved :: MIT License
Classifier: Operating System :: OS Independent
Requires-Python: >=3.6
Requires-Dist: astrosource (>=1.3.0)
